Metadata-Version: 2.1
Name: online-store_Danil_Fedotov
Version: 0.1.2
Summary: Исполняемый пакет для управления пользователями и заказами в онлайн-магазине
Author-email: Fedotov Danil <d.fedotov@edu.centraluniversity.ru>
License: MIT
Requires-Python: >=3.8
Requires-Dist: requests>=2.25.1
Requires-Dist: numpy>=1.19.2
Provides-Extra: dev
Requires-Dist: pytest>=6.2.1; extra == "dev"
Requires-Dist: flake8>=3.8.4; extra == "dev"
